Mclrr_Security/__init__.py
Mclrr_Security-1.0.1.dist-info/LICENSE
Mclrr_Security-1.0.1.dist-info/METADATA
Mclrr_Security-1.0.1.dist-info/WHEEL
Mclrr_Security-1.0.1.dist-info/top_level.txt
Mclrr_Security-1.0.1.dist-info/RECORD
