Metadata-Version: 2.1
Name: Mclrr-Security
Version: 1.0.1
Summary: Package to encode and check passwords
Home-page: https://github.com/maxencerb/Mclrr_Security
Author: Maxence Raballand
Author-email: maxenceraballand00@gmail.com
License: UNKNOWN
Platform: UNKNOWN
Classifier: Programming Language :: Python :: 3
Classifier: License :: OSI Approved :: MIT License
Classifier: Operating System :: OS Independent
Requires-Python: >=3.6
